novaroma_lucas_69/__init__.py
novaroma_lucas_69-0.1.0.dist-info/METADATA
novaroma_lucas_69-0.1.0.dist-info/WHEEL
novaroma_lucas_69-0.1.0.dist-info/entry_points.txt
novaroma_lucas_69-0.1.0.dist-info/RECORD
