Metadata-Version: 2.4
Name: novaroma-lucas-69
Version: 0.1.0
Summary: Aquele episódio
Author-email: João Farias <joaofariastn@gmail.com>
Requires-Python: >=3.11
Requires-Dist: pandas>=2.2.3
